dags/__init__.py
dags/_version.py
dags/annotations.py
dags/dag.py
dags/exceptions.py
dags/output.py
dags/py.typed
dags/signature.py
dags/typing.py
dags/utils.py
dags/tree/__init__.py
dags/tree/dag_tree.py
dags/tree/exceptions.py
dags/tree/tree_utils.py
dags/tree/typing.py
dags/tree/validation.py
dags-0.4.3.dist-info/METADATA
dags-0.4.3.dist-info/WHEEL
dags-0.4.3.dist-info/licenses/LICENSE
dags-0.4.3.dist-info/RECORD
