Metadata-Version: 2.4
Name: dags
Version: 0.4.3
Summary: Tools to create executable dags from interdependent functions.
Project-URL: Repository, https://github.com/OpenSourceEconomics/dags
Project-URL: Github, https://github.com/OpenSourceEconomics/dags
Project-URL: Tracker, https://github.com/OpenSourceEconomics/dags/issues
Author: Tobias Raabe
Author-email: Janoś Gabler <janos.gabler@gmail.com>
Maintainer-email: Hans-Martin von Gaudecker <hmgaudecker@uni-bonn.de>
License: MIT License
License-File: LICENSE
Classifier: Development Status :: 3 - Alpha
Classifier: License :: OSI Approved :: MIT License
Classifier: Operating System :: MacOS :: MacOS X
Classifier: Operating System :: Microsoft :: Windows
Classifier: Operating System :: POSIX
Classifier: Operating System :: Unix
Classifier: Programming Language :: Python :: 3
Classifier: Programming Language :: Python :: 3 :: Only
Classifier: Topic :: Utilities
Classifier: Typing :: Typed
Requires-Python: >=3.10
Requires-Dist: flatten-dict
Requires-Dist: networkx
